eit/EitSupport.py
eit/__init__.py
eit/eitparser.py
eitparser-0.0.1.dist-info/LICENSE
eitparser-0.0.1.dist-info/METADATA
eitparser-0.0.1.dist-info/WHEEL
eitparser-0.0.1.dist-info/top_level.txt
eitparser-0.0.1.dist-info/RECORD
