Metadata-Version: 2.1
Name: eitparser
Version: 0.0.1
Summary: Parser for Event Information Tables
Home-page: https://github.com/WolfgangFahl/eitparser
Author: Wolfgang Fahl
Author-email: wf@bitplan.com
Maintainer: Wolfgang Fahl
License: GPL
Project-URL: Documentation, http://wiki.bitplan.com/index.php/Eitparser
Project-URL: Code, https://github.com/WolfgangFahl/eitparser/blob/main/eit/eitparser.py
Project-URL: Issue tracker, https://github.com/WolfgangFahl/eitparser/issues
Platform: UNKNOWN
Classifier: Programming Language :: Python
Classifier: Programming Language :: Python :: 3.6
Classifier: Programming Language :: Python :: 3.7
Classifier: Programming Language :: Python :: 3.8
Classifier: Programming Language :: Python :: 3.9
